pytel/__init__.py
pytel/context.py
pytel/pytel.py
pytel_inject-0.5.1.dist-info/LICENSE.txt
pytel_inject-0.5.1.dist-info/WHEEL
pytel_inject-0.5.1.dist-info/METADATA
pytel_inject-0.5.1.dist-info/RECORD
