Metadata-Version: 2.1
Name: pytel-inject
Version: 0.5.1
Summary: Injection of dependencies for python 3
Home-page: https://github.com/mattesilver/pytel
License: Apache-2.0
Keywords: injection-of-dependencies,inversion-of-control,guice,spring
Author: Rafal Krupinski
Requires-Python: >=3.6,<4.0
Classifier: License :: OSI Approved :: Apache Software License
Classifier: Programming Language :: Python :: 3
Classifier: Programming Language :: Python :: 3.6
Classifier: Programming Language :: Python :: 3.7
Classifier: Programming Language :: Python :: 3.8
Project-URL: Repository, https://github.com/mattesilver/pytel
